nightlight-1.2.3.dist-info/licenses/LICENSE
simple_config/__init__.py
simple_config/config.py
simple_config/config_builder.py
nightlight-1.2.3.dist-info/METADATA
nightlight-1.2.3.dist-info/WHEEL
nightlight-1.2.3.dist-info/top_level.txt
nightlight-1.2.3.dist-info/RECORD
