Metadata-Version: 2.4
Name: NightLight
Version: 1.2.3
Summary: Basic config reader
Author-email: Mikhail Onuchin <43931801+phntm738@users.noreply.github.com>
Project-URL: Homepage, https://github.com/phntm738/simple-config
Project-URL: Issues, https://github.com/phntm738/simple-config/issues
Classifier: Programming Language :: Python :: 3
Classifier: Operating System :: OS Independent
Classifier: License :: OSI Approved :: MIT License
Requires-Python: >=3.12
License-File: LICENSE
Dynamic: license-file
